aqicn_mcp_server-0.1.0.dist-info/licenses/LICENSE
aqicn_server/__init__.py
aqicn_server/aqicn_server.py
aqicn_mcp_server-0.1.0.dist-info/METADATA
aqicn_mcp_server-0.1.0.dist-info/WHEEL
aqicn_mcp_server-0.1.0.dist-info/entry_points.txt
aqicn_mcp_server-0.1.0.dist-info/top_level.txt
aqicn_mcp_server-0.1.0.dist-info/RECORD
