Metadata-Version: 2.4
Name: aqicn-mcp-server
Version: 0.1.0
Summary: MCP server for fetching air quality data from AQICN
Requires-Python: >=3.13
License-File: LICENSE
Requires-Dist: httpx>=0.28.1
Requires-Dist: mcp[cli]>=1.5.0
Requires-Dist: pydantic>=2.10.6
Requires-Dist: python-dotenv>=1.1.0
Dynamic: license-file
